Orange3_Explain_zh-0.5.3-py3.8-nspkg.pth
orangecontrib/explain/__init__.py
orangecontrib/explain/explainer.py
orangecontrib/explain/inspection.py
orangecontrib/explain/tests/__init__.py
orangecontrib/explain/tests/test_explainer.py
orangecontrib/explain/tests/test_inspection.py
orangecontrib/explain/widgets/__init__.py
orangecontrib/explain/widgets/owexplainfeaturebase.py
orangecontrib/explain/widgets/owexplainmodel.py
orangecontrib/explain/widgets/owexplainprediction.py
orangecontrib/explain/widgets/owexplainpredictions.py
orangecontrib/explain/widgets/owpermutationimportance.py
orangecontrib/explain/widgets/icons/ExplainModel.svg
orangecontrib/explain/widgets/icons/ExplainPred.svg
orangecontrib/explain/widgets/icons/ExplainPredictions.svg
orangecontrib/explain/widgets/icons/PermutationImportance.svg
orangecontrib/explain/widgets/tests/__init__.py
orangecontrib/explain/widgets/tests/test_owexplainmodel.py
orangecontrib/explain/widgets/tests/test_owexplainprediction.py
orangecontrib/explain/widgets/tests/test_owexplainpredictions.py
orangecontrib/explain/widgets/tests/test_owpermutationimportance.py
Orange3_Explain_zh-0.5.3.dist-info/LICENSE.txt
Orange3_Explain_zh-0.5.3.dist-info/METADATA
Orange3_Explain_zh-0.5.3.dist-info/WHEEL
Orange3_Explain_zh-0.5.3.dist-info/entry_points.txt
Orange3_Explain_zh-0.5.3.dist-info/namespace_packages.txt
Orange3_Explain_zh-0.5.3.dist-info/top_level.txt
Orange3_Explain_zh-0.5.3.dist-info/RECORD
