Metadata-Version: 2.1
Name: Orange3-Explain-zh
Version: 0.5.3
Summary: Orange3 add-on for explanatory AI
Home-page: http://orange.biolab.si/download
Author: Bioinformatics Laboratory, FRI UL
Author-email: contact@orange.biolab.si
License: GPL3+
Keywords: orange3 add-on,orange3-explain
Platform: UNKNOWN
Classifier: Development Status :: 4 - Beta
Classifier: Intended Audience :: Science/Research
Classifier: Programming Language :: Python :: 3 :: Only
License-File: LICENSE.txt
Requires-Dist: Orange3-zh (>=3.28.0)
Requires-Dist: AnyQt
Requires-Dist: numpy
Requires-Dist: pyqtgraph
Requires-Dist: scipy
Requires-Dist: shap (==0.40.*)
Provides-Extra: doc
Requires-Dist: sphinx ; extra == 'doc'
Requires-Dist: recommonmark ; extra == 'doc'
Requires-Dist: sphinx-rtd-theme ; extra == 'doc'
Provides-Extra: test
Requires-Dist: pytest ; extra == 'test'
Requires-Dist: coverage ; extra == 'test'
